knw_Chromedriver_manager/Chromedriver_manager.py
knw_Chromedriver_manager/__init__.py
knw_Chromedriver_manager-0.2.2.dist-info/METADATA
knw_Chromedriver_manager-0.2.2.dist-info/WHEEL
knw_Chromedriver_manager-0.2.2.dist-info/top_level.txt
knw_Chromedriver_manager-0.2.2.dist-info/RECORD
