Metadata-Version: 2.1
Name: knw_Chromedriver_manager
Version: 0.2.2
Home-page: https://github.com/daumsong/knw_webdriver_manager
Author: archon.oh
Author-email: archon.oh@knworks.co.kr
Keywords: knw,webdriver,manager,selenium
Requires-Python: >=3.6
Requires-Dist: requests
